alibabacloud_cloudapi20160714/__init__.py
alibabacloud_cloudapi20160714/client.py
alibabacloud_cloudapi20160714/models/__init__.py
alibabacloud_cloudapi20160714/models/_abolish_api_request.py
alibabacloud_cloudapi20160714/models/_abolish_api_response.py
alibabacloud_cloudapi20160714/models/_abolish_api_response_body.py
alibabacloud_cloudapi20160714/models/_add_access_control_list_entry_request.py
alibabacloud_cloudapi20160714/models/_add_access_control_list_entry_response.py
alibabacloud_cloudapi20160714/models/_add_access_control_list_entry_response_body.py
alibabacloud_cloudapi20160714/models/_add_ip_control_policy_item_request.py
alibabacloud_cloudapi20160714/models/_add_ip_control_policy_item_response.py
alibabacloud_cloudapi20160714/models/_add_ip_control_policy_item_response_body.py
alibabacloud_cloudapi20160714/models/_add_traffic_special_control_request.py
alibabacloud_cloudapi20160714/models/_add_traffic_special_control_response.py
alibabacloud_cloudapi20160714/models/_add_traffic_special_control_response_body.py
alibabacloud_cloudapi20160714/models/_associate_instance_with_private_dnsrequest.py
alibabacloud_cloudapi20160714/models/_associate_instance_with_private_dnsresponse.py
alibabacloud_cloudapi20160714/models/_associate_instance_with_private_dnsresponse_body.py
alibabacloud_cloudapi20160714/models/_associate_instance_with_private_dnsshrink_request.py
alibabacloud_cloudapi20160714/models/_attach_api_product_request.py
alibabacloud_cloudapi20160714/models/_attach_api_product_response.py
alibabacloud_cloudapi20160714/models/_attach_api_product_response_body.py
alibabacloud_cloudapi20160714/models/_attach_group_plugin_request.py
alibabacloud_cloudapi20160714/models/_attach_group_plugin_response.py
alibabacloud_cloudapi20160714/models/_attach_group_plugin_response_body.py
alibabacloud_cloudapi20160714/models/_attach_plugin_request.py
alibabacloud_cloudapi20160714/models/_attach_plugin_response.py
alibabacloud_cloudapi20160714-4.8.9.dist-info/LICENSE
alibabacloud_cloudapi20160714-4.8.9.dist-info/METADATA
alibabacloud_cloudapi20160714-4.8.9.dist-info/WHEEL
alibabacloud_cloudapi20160714-4.8.9.dist-info/top_level.txt
alibabacloud_cloudapi20160714-4.8.9.dist-info/RECORD
